{
  "@id": "https://doi.org/10.239823/sdkje-jdf",
  "url": "https://doi.org/10.239823/sdkje-jdf",
  "name": "Development of coral reefs under climate change impacts and adaptation options",
  "@type": "SoftwareSourceCode",
  "author": [
    {
      "@id": "http://localhost:8000/users/3325/",
      "@type": "Person",
      "email": "comsesadmin@mailinator.com",
      "givenName": "Admin",
      "familyName": "User",
      "affiliation": {
        "@id": "https://ror.org/03efmqc40",
        "url": "https://www.asu.edu",
        "name": "Arizona State University",
        "@type": "Organization",
        "identifier": "https://ror.org/03efmqc40"
      }
    },
    {
      "@id": "http://localhost:8000/users/3326/",
      "@type": "Person",
      "email": "comsestestuser@mailinator.com",
      "givenName": "Test",
      "familyName": "User"
    },
    {
      "@id": "_:author_3",
      "@type": "Person",
      "email": "ahjsdfhjajshdkf@example.com",
      "givenName": "asdfasdf",
      "familyName": "asdfasdfasdf"
    },
    {
      "@id": "_:author_4",
      "@type": "Person",
      "email": "wdwdwdwdwd@example.com",
      "givenName": "wwwwwwwww",
      "familyName": "zzzzzz"
    },
    {
      "@id": "_:author_5",
      "@type": "Person",
      "email": "asdasd@example.com",
      "givenName": "awdawdawd",
      "familyName": "wwwwwddddd"
    },
    {
      "@id": "_:author_6",
      "@type": "Person",
      "email": "asda@example.com",
      "givenName": "wwwwwwww",
      "familyName": "zzzzzzzzzzzzzzz"
    },
    {
      "@id": "http://localhost:8000/users/3325/",
      "@type": "Role",
      "roleName": "funder"
    },
    {
      "@id": "_:author_4",
      "@type": "Role",
      "roleName": "contributor"
    }
  ],
  "license": {
    "url": "http://www.gnu.org/licenses/gpl-2.0.html",
    "name": "GPL-2.0",
    "@type": "CreativeWork"
  },
  "version": "10.1.0",
  "@context": "https://w3id.org/codemeta/3.0",
  "publisher": {
    "@id": "https://ror.org/015bsfc29",
    "url": "https://www.comses.net",
    "name": "CoMSES Net",
    "@type": "Organization"
  },
  "identifier": [
    "10.239823/sdkje-jdf",
    "https://doi.org/10.239823/sdkje-jdf"
  ],
  "dateCreated": "2025-06-03",
  "description": "testing github publishing jan 2025",
  "downloadUrl": "http://localhost:8000/codebases/33abc5db-781e-443f-8df4-fdcd88e8fdf9/releases/10.1.0/download/",
  "dateModified": "2025-06-05",
  "releaseNotes": "o0o0o",
  "copyrightYear": 2025,
  "datePublished": "2025-06-03",
  "operatingSystem": "platform_independent",
  "runtimePlatform": [
    "python"
  ],
  "applicationCategory": "Computational Model",
  "programmingLanguage": [
    {
      "name": "coffee",
      "@type": "ComputerLanguage"
    }
  ]
}